heatmap_generator/__init__.py
heatmap_generator/heatmap_generator.py
heatmap_generator/heatmap_generator_test.py
heatmap_generator-0.1.2.dist-info/METADATA
heatmap_generator-0.1.2.dist-info/WHEEL
heatmap_generator-0.1.2.dist-info/top_level.txt
heatmap_generator-0.1.2.dist-info/RECORD
